{
  "signedContributors": [
    {
      "name": "AnandChowdhary",
      "id": 2841780,
      "comment_id": 669143169,
      "created_at": "2020-08-05T11:36:56Z",
      "repoId": 276858968,
      "pullRequestNo": 56
    },
    {
      "name": "KojBot",
      "id": 67733299,
      "comment_id": 669147408,
      "created_at": "2020-08-05T11:47:56Z",
      "repoId": 276858968,
      "pullRequestNo": 57
    },
    {
      "name": "CleverclipBot",
      "id": 68742214,
      "comment_id": 669935979,
      "created_at": "2020-08-06T13:45:36Z",
      "repoId": 276858968,
      "pullRequestNo": 62
    },
    {
      "name": "AndrewLaneX",
      "id": 32808683,
      "comment_id": 716271334,
      "created_at": "2020-10-26T02:42:42Z",
      "repoId": 303741388,
      "pullRequestNo": 12
    },
    {
      "name": "CompuGenius",
      "id": 39806174,
      "comment_id": 718287300,
      "created_at": "2020-10-29T00:38:37Z",
      "repoId": 303730837,
      "pullRequestNo": 33
    },
    {
      "name": "akoenig",
      "id": 224910,
      "comment_id": 727275243,
      "created_at": "2020-11-14T22:39:41Z",
      "repoId": 303730837,
      "pullRequestNo": 52
    },
    {
      "name": "Gerhut",
      "id": 2500247,
      "comment_id": 731901615,
      "created_at": "2020-11-23T02:55:08Z",
      "repoId": 303730837,
      "pullRequestNo": 64
    },
    {
      "name": "aureooms",
      "id": 5165674,
      "comment_id": 732265032,
      "created_at": "2020-11-23T16:16:41Z",
      "repoId": 303730837,
      "pullRequestNo": 68
    },
    {
      "name": "fcjr",
      "id": 2053002,
      "comment_id": 734150497,
      "created_at": "2020-11-26T08:26:39Z",
      "repoId": 303730837,
      "pullRequestNo": 74
    },
    {
      "name": "billchenchina",
      "id": 7758042,
      "comment_id": 735350882,
      "created_at": "2020-11-29T06:29:11Z",
      "repoId": 303741388,
      "pullRequestNo": 50
    },
    {
      "name": "rzkmak",
      "id": 12380302,
      "comment_id": 751799510,
      "created_at": "2020-12-28T17:32:05Z",
      "repoId": 303741388,
      "pullRequestNo": 81
    },
    {
      "name": "mikechernev",
      "id": 1446450,
      "comment_id": 754783007,
      "created_at": "2021-01-05T17:32:30Z",
      "repoId": 303741388,
      "pullRequestNo": 86
    },
    {
      "name": "dstroot",
      "id": 1438457,
      "comment_id": 756490586,
      "created_at": "2021-01-08T01:32:10Z",
      "repoId": 303730837,
      "pullRequestNo": 124
    },
    {
      "name": "ConcurrentHashMap",
      "id": 7402908,
      "comment_id": 757711080,
      "created_at": "2021-01-11T08:29:09Z",
      "repoId": 303730837,
      "pullRequestNo": 126
    },
    {
      "name": "vladzaharia",
      "id": 79390,
      "comment_id": 766287014,
      "created_at": "2021-01-24T03:56:40Z",
      "repoId": 303741388,
      "pullRequestNo": 102
    },
    {
      "name": "rcdailey",
      "id": 1768054,
      "comment_id": 782953908,
      "created_at": "2021-02-21T23:53:08Z",
      "repoId": 303741388,
      "pullRequestNo": 122
    }
  ]
}